ss_gcj02towgs84/GCJ02toWGS84.py
ss_gcj02towgs84/__init__.py
ss_gcj02towgs84/server.py
ss_gcj02towgs84-0.1.0.dist-info/METADATA
ss_gcj02towgs84-0.1.0.dist-info/WHEEL
ss_gcj02towgs84-0.1.0.dist-info/entry_points.txt
ss_gcj02towgs84-0.1.0.dist-info/RECORD
