Metadata-Version: 2.4
Name: ss-gcj02towgs84
Version: 0.1.0
Summary: Add your description here
Author-email: 王强 <729739793@qq.com>
Requires-Python: >=3.10
Requires-Dist: fastmcp
Requires-Dist: fastmcp>=2.10.1
Requires-Dist: mcp[cli]>=1.10.1
